agvd.py
cli.py
core.py
exceptions.py
query.py
utils.py
agvd-0.1.2.dist-info/METADATA
agvd-0.1.2.dist-info/WHEEL
agvd-0.1.2.dist-info/entry_points.txt
agvd-0.1.2.dist-info/top_level.txt
agvd-0.1.2.dist-info/RECORD
