Metadata-Version: 2.1
Name: agvd
Version: 0.1.2
Summary: AGVD Variant Query Command Line Tool
Home-page: https://github.com/wmudaki/agvdPy
Author: WMudaki
Author-email: wilson@mudaki.co.ke
Classifier: Programming Language :: Python :: 3
Classifier: License :: OSI Approved :: MIT License
Classifier: Operating System :: OS Independent
Requires-Python: >=3.7
Requires-Dist: pysam
Requires-Dist: tqdm
Requires-Dist: requests
Requires-Dist: pandas
Requires-Dist: openpyxl
